factoree_ai_pipeline/__init__.py
factoree_ai_pipeline/bronze_to_silver_runner.py
factoree_ai_pipeline/file/__init__.py
factoree_ai_pipeline/file/file_types.py
factoree_ai_pipeline/file/file_utils.py
factoree_ai_pipeline/s3/__init__.py
factoree_ai_pipeline/s3/formatted_s3_source_connector.py
factoree_ai_pipeline/s3/s3_client.py
factoree_ai_pipeline/s3/s3_client_utils.py
factoree_ai_pipeline/s3/s3_connector.py
factoree_ai_pipeline/s3/s3_sink_connector.py
factoree_ai_pipeline/s3/s3_source_connector.py
factoree_ai_pipeline/s3/s3_utility.py
factoree_ai_pipeline/sensor_type.py
factoree_ai_pipeline/sqs/__init__.py
factoree_ai_pipeline/sqs/sqs_utils.py
factoree_ai_pipeline/system_params.py
factoree_ai_pipeline/text/__init__.py
factoree_ai_pipeline/text/text_parsers.py
factoree_ai_pipeline/text/text_utils.py
factoree_ai_pipeline/transform/__init__.py
factoree_ai_pipeline/transform/csv_transform_utility.py
factoree_ai_pipeline/transform/transform_utility.py
factoree_ai_pipeline-2.2.7.dist-info/METADATA
factoree_ai_pipeline-2.2.7.dist-info/WHEEL
factoree_ai_pipeline-2.2.7.dist-info/LICENSE
factoree_ai_pipeline-2.2.7.dist-info/RECORD
