Metadata-Version: 2.1
Name: factoree-ai-pipeline
Version: 2.2.7
Summary: 
Author: zheni
Author-email: evgeniya@factoree.ai
Requires-Python: >=3.10.5,<4.0.0
Classifier: Programming Language :: Python :: 3
Classifier: Programming Language :: Python :: 3.11
Requires-Dist: boto3 (>=1.24.82,<2.0.0)
Requires-Dist: dotenv-config (>=0.1.4,<0.2.0)
Requires-Dist: flake8 (>=6.0.0,<7.0.0)
Requires-Dist: pytz (>=2022.6,<2023.0)
Requires-Dist: requests (>=2.28.0,<3.0.0)
Requires-Dist: tzdata (>=2022.7,<2023.0)
